[
  {
    "id": 1,
    "title": "111",
    "content": "111",
    "author": "eddie",
    "timestamp": "2024-09-20 09:52:49",
    "comments": [
      {
        "author": "eddie",
        "content": "\u8fd9\u662f\u4e2a\u5565",
        "timestamp": "2024-09-20 10:03:21"
      },
      {
        "author": "eddie",
        "content": "\u6211\u89c9\u5f97\u884c",
        "timestamp": "2024-09-20 10:04:57"
      }
    ]
  },
  {
    "id": 2,
    "title": "bt1",
    "content": "1111",
    "author": "eddie",
    "timestamp": "2024-09-20 10:05:33",
    "comments": []
  },
  {
    "id": 3,
    "title": "bt1",
    "content": "2222",
    "author": "eddie",
    "timestamp": "2024-09-20 10:08:57",
    "comments": [],
    "image": "yjtp.png"
  },
  {
    "id": 4,
    "title": "\u521a\u521a",
    "content": "\u591f",
    "author": "eddie",
    "timestamp": "2024-09-20 10:11:57",
    "comments": [],
    "image": "dog-leash-types.jpg"
  }
]
